{"_type":"export","__export_format":4,"__export_date":"2023-04-16T20:01:56.888Z","__export_source":"insomnia.desktop.app:v2023.1.0","resources":[{"_id":"req_cd3dd9157120404aad2f41d935ce6756","parentId":"wrk_967499610c14465b8401db18140c22d1","modified":1681675194868,"created":1681500033817,"url":"localhost:5000/variables/22d7bdb0-2172-11e4-813c-005056900044","name":"Get question - ✅","description":"","method":"GET","body":{},"parameters":[],"headers":[],"authentication":{},"metaSortKey":-1681597356695.125,"isPrivate":false,"settingStoreCookies":true,"settingSendCookies":true,"settingDisableRenderRequestBody":false,"settingEncodeUrl":true,"settingRebuildPath":true,"settingFollowRedirects":"global","_type":"request"},{"_id":"wrk_967499610c14465b8401db18140c22d1","parentId":null,"modified":1681500031126,"created":1681500031126,"name":"YouGov Challenge","description":"","scope":"collection","_type":"workspace"},{"_id":"req_a7eea034ab344ac18b961d3d11892bf2","parentId":"wrk_967499610c14465b8401db18140c22d1","modified":1681665528095,"created":1681603844887,"url":"localhost:5000/variables/22d7bdb0-2172-11e4-813c-005056900044/counts","name":"Get answers count - ✅","description":"","method":"GET","body":{},"parameters":[],"headers":[],"authentication":{},"metaSortKey":-1681597356645.125,"isPrivate":false,"settingStoreCookies":true,"settingSendCookies":true,"settingDisableRenderRequestBody":false,"settingEncodeUrl":true,"settingRebuildPath":true,"settingFollowRedirects":"global","_type":"request"},{"_id":"req_9e3e2c83a63243839386d51460725ed7","parentId":"wrk_967499610c14465b8401db18140c22d1","modified":1681665538913,"created":1681665432419,"url":"localhost:5000/variables/123","name":"Get question - ❌","description":"","method":"GET","body":{},"parameters":[],"headers":[],"authentication":{},"metaSortKey":-1681597356595.125,"isPrivate":false,"settingStoreCookies":true,"settingSendCookies":true,"settingDisableRenderRequestBody":false,"settingEncodeUrl":true,"settingRebuildPath":true,"settingFollowRedirects":"global","_type":"request"},{"_id":"req_84bd328a27a344bfac0b583cbf7f5ff7","parentId":"wrk_967499610c14465b8401db18140c22d1","modified":1681665764427,"created":1681665471088,"url":"localhost:5000/variables/123/counts","name":"Get answers count - ❌","description":"","method":"GET","body":{},"parameters":[],"headers":[],"authentication":{},"metaSortKey":-1681597356545.125,"isPrivate":false,"settingStoreCookies":true,"settingSendCookies":true,"settingDisableRenderRequestBody":false,"settingEncodeUrl":true,"settingRebuildPath":true,"settingFollowRedirects":"global","_type":"request"},{"_id":"env_884e973f8ae6b2954207af476cc2ed680d1ea6f8","parentId":"wrk_967499610c14465b8401db18140c22d1","modified":1681500031129,"created":1681500031129,"name":"Base Environment","data":{},"dataPropertyOrder":null,"color":null,"isPrivate":false,"metaSortKey":1681500031129,"_type":"environment"},{"_id":"jar_884e973f8ae6b2954207af476cc2ed680d1ea6f8","parentId":"wrk_967499610c14465b8401db18140c22d1","modified":1681500031130,"created":1681500031130,"name":"Default Jar","cookies":[],"_type":"cookie_jar"},{"_id":"spc_df838e79dfe5445ba9c35af5b6dd6829","parentId":"wrk_967499610c14465b8401db18140c22d1","modified":1681500031127,"created":1681500031127,"fileName":"YouGov Challenge","contents":"","contentType":"yaml","_type":"api_spec"}]}